{
  "batch_info": {
    "batch_number": 34,
    "total_batches": 613,
    "start_index": 1650,
    "end_index": 1700,
    "total_transactions": 30640,
    "batch_size": 50,
    "timestamp": "20250818_144743"
  },
  "results": [
    {
      "txid": "1b9c791c97a8971f5b798291cf21c6532f7dcb24811c7553daefec6a4670e37d",
      "is_coinjoin": true,
      "detection_method": "wasabi",
      "score": 0.5,
      "reasons": [
        "Wasabi heuristic detection (0.1 BTC pattern)"
      ],
      "indicators": {
        "input_count": 83,
        "output_count": 110,
        "unique_input_addresses": 83,
        "unique_output_addresses": 110,
        "output_uniformity": 42,
        "input_diversity": 83,
        "transaction_size": 193
      },
      "wasabi_detected": true,
      "samourai_detected": false,
      "uniformity_score": 0.509090909090909,
      "diversity_score": 1.0,
      "timestamp": "2025-08-18T14:46:55.769777"
    },
    {
      "txid": "e2b1eff57e447ea4c02d527b4b203447d062111635c84975ba11590cac2f6fbb",
      "is_coinjoin": true,
      "detection_method": "wasabi",
      "score": 0.4,
      "reasons": [
        "Wasabi static detection (coordinator + equal outputs)",
        "Wasabi heuristic detection (0.1 BTC pattern)"
      ],
      "indicators": {
        "input_count": 116,
        "output_count": 163,
        "unique_input_addresses": 116,
        "unique_output_addresses": 163,
        "output_uniformity": 53,
        "input_diversity": 116,
        "transaction_size": 279
      },
      "wasabi_detected": true,
      "samourai_detected": false,
      "uniformity_score": 0.5153374233128835,
      "diversity_score": 1.0,
      "timestamp": "2025-08-18T14:46:56.956754"
    },
    {
      "txid": "d3c5045dc7b615dc9bc85c9f0535d473f748fdbd029f128ae32981377842d774",
      "is_coinjoin": true,
      "detection_method": "wasabi",
      "score": 0.5,
      "reasons": [
        "Wasabi static detection (coordinator + equal outputs)",
        "Wasabi heuristic detection (0.1 BTC pattern)"
      ],
      "indicators": {
        "input_count": 42,
        "output_count": 58,
        "unique_input_addresses": 42,
        "unique_output_addresses": 58,
        "output_uniformity": 18,
        "input_diversity": 42,
        "transaction_size": 100
      },
      "wasabi_detected": true,
      "samourai_detected": false,
      "uniformity_score": 0.7068965517241379,
      "diversity_score": 1.0,
      "timestamp": "2025-08-18T14:46:57.977361"
    },
    {
      "txid": "1f8e3b77792d8583d1d1ae68cfe4244b562456d329134c9e1881acc15c8481f4",
      "is_coinjoin": true,
      "detection_method": "wasabi",
      "score": 0.4,
      "reasons": [
        "Wasabi heuristic detection (0.1 BTC pattern)"
      ],
      "indicators": {
        "input_count": 99,
        "output_count": 141,
        "unique_input_addresses": 99,
        "unique_output_addresses": 141,
        "output_uniformity": 59,
        "input_diversity": 99,
        "transaction_size": 240
      },
      "wasabi_detected": true,
      "samourai_detected": false,
      "uniformity_score": 0.48936170212765956,
      "diversity_score": 1.0,
      "timestamp": "2025-08-18T14:46:59.057456"
    },
    {
      "txid": "bc53867912acb72861415828c2d2dcf81f38c1beb8985d8c5f74e795dcca8165",
      "is_coinjoin": true,
      "detection_method": "wasabi",
      "score": 0.4,
      "reasons": [
        "Wasabi static detection (coordinator + equal outputs)",
        "Wasabi heuristic detection (0.1 BTC pattern)"
      ],
      "indicators": {
        "input_count": 114,
        "output_count": 208,
        "unique_input_addresses": 114,
        "unique_output_addresses": 208,
        "output_uniformity": 68,
        "input_diversity": 114,
        "transaction_size": 322
      },
      "wasabi_detected": true,
      "samourai_detected": false,
      "uniformity_score": 0.4182692307692308,
      "diversity_score": 1.0,
      "timestamp": "2025-08-18T14:47:00.298491"
    },
    {
      "txid": "fbfde81464d22fa004c619f0b039b5c791ec626a20336aa4b78d719ef0ac7eea",
      "is_coinjoin": true,
      "detection_method": "wasabi",
      "score": 0.5,
      "reasons": [
        "Wasabi static detection (coordinator + equal outputs)",
        "Wasabi heuristic detection (0.1 BTC pattern)"
      ],
      "indicators": {
        "input_count": 66,
        "output_count": 99,
        "unique_input_addresses": 66,
        "unique_output_addresses": 99,
        "output_uniformity": 34,
        "input_diversity": 66,
        "transaction_size": 165
      },
      "wasabi_detected": true,
      "samourai_detected": false,
      "uniformity_score": 0.47474747474747475,
      "diversity_score": 1.0,
      "timestamp": "2025-08-18T14:47:01.365641"
    },
    {
      "txid": "d1581987aea997b0d0f2fefb7c8dfc545d5a4afb43ce9779c7ac5dfd29eff9c1",
      "is_coinjoin": true,
      "detection_method": "wasabi",
      "score": 0.5,
      "reasons": [
        "Wasabi heuristic detection (0.1 BTC pattern)"
      ],
      "indicators": {
        "input_count": 34,
        "output_count": 61,
        "unique_input_addresses": 34,
        "unique_output_addresses": 61,
        "output_uniformity": 24,
        "input_diversity": 34,
        "transaction_size": 95
      },
      "wasabi_detected": true,
      "samourai_detected": false,
      "uniformity_score": 0.45901639344262296,
      "diversity_score": 1.0,
      "timestamp": "2025-08-18T14:47:02.379254"
    },
    {
      "txid": "76b492da49dda6f744fd6db55fe3ea8a653052a3f240092c4713bfa370b8521f",
      "is_coinjoin": true,
      "detection_method": "wasabi",
      "score": 0.5,
      "reasons": [
        "Wasabi heuristic detection (0.1 BTC pattern)"
      ],
      "indicators": {
        "input_count": 54,
        "output_count": 87,
        "unique_input_addresses": 53,
        "unique_output_addresses": 87,
        "output_uniformity": 34,
        "input_diversity": 53,
        "transaction_size": 141
      },
      "wasabi_detected": true,
      "samourai_detected": false,
      "uniformity_score": 0.4827586206896552,
      "diversity_score": 0.9814814814814815,
      "timestamp": "2025-08-18T14:47:03.415355"
    },
    {
      "txid": "94a660e01df108ef3fc0527b773b4b1a9c75fd8eb214066d63077e19679c8c55",
      "is_coinjoin": true,
      "detection_method": "wasabi",
      "score": 0.5,
      "reasons": [
        "Wasabi static detection (coordinator + equal outputs)",
        "Wasabi heuristic detection (0.1 BTC pattern)"
      ],
      "indicators": {
        "input_count": 68,
        "output_count": 129,
        "unique_input_addresses": 68,
        "unique_output_addresses": 129,
        "output_uniformity": 49,
        "input_diversity": 68,
        "transaction_size": 197
      },
      "wasabi_detected": true,
      "samourai_detected": false,
      "uniformity_score": 0.4496124031007752,
      "diversity_score": 1.0,
      "timestamp": "2025-08-18T14:47:04.440940"
    },
    {
      "txid": "726a230659f97c224c76b343ca6d9389c24b0ab4f290571bc35695859541b308",
      "is_coinjoin": true,
      "detection_method": "wasabi",
      "score": 0.4,
      "reasons": [
        "Wasabi static detection (coordinator + equal outputs)",
        "Wasabi heuristic detection (0.1 BTC pattern)"
      ],
      "indicators": {
        "input_count": 88,
        "output_count": 163,
        "unique_input_addresses": 88,
        "unique_output_addresses": 163,
        "output_uniformity": 57,
        "input_diversity": 88,
        "transaction_size": 251
      },
      "wasabi_detected": true,
      "samourai_detected": false,
      "uniformity_score": 0.4233128834355828,
      "diversity_score": 1.0,
      "timestamp": "2025-08-18T14:47:05.592573"
    },
    {
      "txid": "c9ec2d063a2a3bf5933f9a81c45ad5434ec0be41ab5dde13f80f2b3326675991",
      "is_coinjoin": true,
      "detection_method": "wasabi",
      "score": 0.5,
      "reasons": [
        "Wasabi heuristic detection (0.1 BTC pattern)"
      ],
      "indicators": {
        "input_count": 71,
        "output_count": 119,
        "unique_input_addresses": 71,
        "unique_output_addresses": 119,
        "output_uniformity": 53,
        "input_diversity": 71,
        "transaction_size": 190
      },
      "wasabi_detected": true,
      "samourai_detected": false,
      "uniformity_score": 0.453781512605042,
      "diversity_score": 1.0,
      "timestamp": "2025-08-18T14:47:06.661763"
    },
    {
      "txid": "9668cd1b2be7aee3b5e41e6a3153469689c8b0a5f06dc1934f5221e02a7397e6",
      "is_coinjoin": true,
      "detection_method": "wasabi",
      "score": 0.5,
      "reasons": [
        "Wasabi heuristic detection (0.1 BTC pattern)"
      ],
      "indicators": {
        "input_count": 72,
        "output_count": 126,
        "unique_input_addresses": 72,
        "unique_output_addresses": 126,
        "output_uniformity": 50,
        "input_diversity": 72,
        "transaction_size": 198
      },
      "wasabi_detected": true,
      "samourai_detected": false,
      "uniformity_score": 0.47619047619047616,
      "diversity_score": 1.0,
      "timestamp": "2025-08-18T14:47:07.671653"
    },
    {
      "txid": "d942f2adc587c6f030938dafe375554ffaeb57465924627d7663ac22cc96cc86",
      "is_coinjoin": true,
      "detection_method": "wasabi",
      "score": 0.5,
      "reasons": [
        "Wasabi static detection (coordinator + equal outputs)",
        "Wasabi heuristic detection (0.1 BTC pattern)"
      ],
      "indicators": {
        "input_count": 41,
        "output_count": 66,
        "unique_input_addresses": 41,
        "unique_output_addresses": 66,
        "output_uniformity": 26,
        "input_diversity": 41,
        "transaction_size": 107
      },
      "wasabi_detected": true,
      "samourai_detected": false,
      "uniformity_score": 0.6212121212121212,
      "diversity_score": 1.0,
      "timestamp": "2025-08-18T14:47:08.712008"
    },
    {
      "txid": "87515982f2ab437d4289f48a1c17974f147b8ddc90147f81aba2c3c092b5f260",
      "is_coinjoin": true,
      "detection_method": "wasabi",
      "score": 0.5,
      "reasons": [
        "Wasabi static detection (coordinator + equal outputs)",
        "Wasabi heuristic detection (0.1 BTC pattern)"
      ],
      "indicators": {
        "input_count": 44,
        "output_count": 67,
        "unique_input_addresses": 44,
        "unique_output_addresses": 67,
        "output_uniformity": 26,
        "input_diversity": 44,
        "transaction_size": 111
      },
      "wasabi_detected": true,
      "samourai_detected": false,
      "uniformity_score": 0.5373134328358209,
      "diversity_score": 1.0,
      "timestamp": "2025-08-18T14:47:09.716388"
    },
    {
      "txid": "a7e4cf6bed48065caf58114783ed3360b7524f0bcee675d10575627af1cab852",
      "is_coinjoin": true,
      "detection_method": "wasabi",
      "score": 0.4,
      "reasons": [
        "Wasabi heuristic detection (0.1 BTC pattern)"
      ],
      "indicators": {
        "input_count": 131,
        "output_count": 205,
        "unique_input_addresses": 131,
        "unique_output_addresses": 205,
        "output_uniformity": 75,
        "input_diversity": 131,
        "transaction_size": 336
      },
      "wasabi_detected": true,
      "samourai_detected": false,
      "uniformity_score": 0.4682926829268293,
      "diversity_score": 1.0,
      "timestamp": "2025-08-18T14:47:10.937555"
    },
    {
      "txid": "a42e40508987e6c51926a1e6d43584d03091c99f0d465ca3e736f748e3a4146a",
      "is_coinjoin": true,
      "detection_method": "wasabi",
      "score": 0.4,
      "reasons": [
        "Wasabi static detection (coordinator + equal outputs)",
        "Wasabi heuristic detection (0.1 BTC pattern)"
      ],
      "indicators": {
        "input_count": 123,
        "output_count": 156,
        "unique_input_addresses": 120,
        "unique_output_addresses": 156,
        "output_uniformity": 62,
        "input_diversity": 120,
        "transaction_size": 279
      },
      "wasabi_detected": true,
      "samourai_detected": false,
      "uniformity_score": 0.5256410256410257,
      "diversity_score": 0.975609756097561,
      "timestamp": "2025-08-18T14:47:12.123430"
    },
    {
      "txid": "7f5e77992e8a41c5b6e37cf7f9eb4822e4a9c0f2378149782f6f69bcaf389a0c",
      "is_coinjoin": true,
      "detection_method": "wasabi",
      "score": 0.5,
      "reasons": [
        "Wasabi heuristic detection (0.1 BTC pattern)"
      ],
      "indicators": {
        "input_count": 46,
        "output_count": 68,
        "unique_input_addresses": 46,
        "unique_output_addresses": 68,
        "output_uniformity": 22,
        "input_diversity": 46,
        "transaction_size": 114
      },
      "wasabi_detected": true,
      "samourai_detected": false,
      "uniformity_score": 0.6029411764705882,
      "diversity_score": 1.0,
      "timestamp": "2025-08-18T14:47:13.157341"
    },
    {
      "txid": "1dd9c9faec79e8d037a69eefd8611f56b8e83a1151170c46e42482687b082cd9",
      "is_coinjoin": true,
      "detection_method": "wasabi",
      "score": 0.4,
      "reasons": [
        "Wasabi static detection (coordinator + equal outputs)",
        "Wasabi heuristic detection (0.1 BTC pattern)"
      ],
      "indicators": {
        "input_count": 109,
        "output_count": 145,
        "unique_input_addresses": 108,
        "unique_output_addresses": 145,
        "output_uniformity": 57,
        "input_diversity": 108,
        "transaction_size": 254
      },
      "wasabi_detected": true,
      "samourai_detected": false,
      "uniformity_score": 0.5517241379310345,
      "diversity_score": 0.9908256880733946,
      "timestamp": "2025-08-18T14:47:14.248416"
    },
    {
      "txid": "b0932a904e4085eab72feb71920a157f74f232a039291ba0ef0c574d4e869640",
      "is_coinjoin": true,
      "detection_method": "wasabi",
      "score": 0.5,
      "reasons": [
        "Wasabi heuristic detection (0.1 BTC pattern)"
      ],
      "indicators": {
        "input_count": 72,
        "output_count": 107,
        "unique_input_addresses": 72,
        "unique_output_addresses": 107,
        "output_uniformity": 44,
        "input_diversity": 72,
        "transaction_size": 179
      },
      "wasabi_detected": true,
      "samourai_detected": false,
      "uniformity_score": 0.5327102803738317,
      "diversity_score": 1.0,
      "timestamp": "2025-08-18T14:47:15.292053"
    },
    {
      "txid": "262228db1e637bfe7303d20b5b26c13e6e4327dde499e852c04bc77136dcdb99",
      "is_coinjoin": true,
      "detection_method": "wasabi",
      "score": 0.5,
      "reasons": [
        "Wasabi static detection (coordinator + equal outputs)",
        "Wasabi heuristic detection (0.1 BTC pattern)"
      ],
      "indicators": {
        "input_count": 46,
        "output_count": 66,
        "unique_input_addresses": 46,
        "unique_output_addresses": 66,
        "output_uniformity": 26,
        "input_diversity": 46,
        "transaction_size": 112
      },
      "wasabi_detected": true,
      "samourai_detected": false,
      "uniformity_score": 0.6212121212121212,
      "diversity_score": 1.0,
      "timestamp": "2025-08-18T14:47:16.299361"
    },
    {
      "txid": "fd16e92bfae6d4fc5e2056b3e934b3ba7c2b2848e20de58523536d4cdc35280c",
      "is_coinjoin": true,
      "detection_method": "wasabi",
      "score": 0.4,
      "reasons": [
        "Wasabi static detection (coordinator + equal outputs)",
        "Wasabi heuristic detection (0.1 BTC pattern)"
      ],
      "indicators": {
        "input_count": 85,
        "output_count": 144,
        "unique_input_addresses": 85,
        "unique_output_addresses": 144,
        "output_uniformity": 47,
        "input_diversity": 85,
        "transaction_size": 229
      },
      "wasabi_detected": true,
      "samourai_detected": false,
      "uniformity_score": 0.4652777777777778,
      "diversity_score": 1.0,
      "timestamp": "2025-08-18T14:47:17.369382"
    },
    {
      "txid": "2e6e643665df9cd7cc92192df0c2b401953dc2a5f995f97adde1ae0ffe8a5f94",
      "is_coinjoin": true,
      "detection_method": "wasabi",
      "score": 0.5,
      "reasons": [
        "Wasabi heuristic detection (0.1 BTC pattern)"
      ],
      "indicators": {
        "input_count": 13,
        "output_count": 23,
        "unique_input_addresses": 13,
        "unique_output_addresses": 23,
        "output_uniformity": 11,
        "input_diversity": 13,
        "transaction_size": 36
      },
      "wasabi_detected": true,
      "samourai_detected": false,
      "uniformity_score": 0.5652173913043478,
      "diversity_score": 1.0,
      "timestamp": "2025-08-18T14:47:18.222934"
    },
    {
      "txid": "5a31c46683ec45540999f5aa01dd7da36b1ca7930bdf632661ded30bc8d4bd5c",
      "is_coinjoin": true,
      "detection_method": "wasabi",
      "score": 0.4,
      "reasons": [
        "Wasabi heuristic detection (0.1 BTC pattern)"
      ],
      "indicators": {
        "input_count": 115,
        "output_count": 200,
        "unique_input_addresses": 114,
        "unique_output_addresses": 200,
        "output_uniformity": 79,
        "input_diversity": 114,
        "transaction_size": 315
      },
      "wasabi_detected": true,
      "samourai_detected": false,
      "uniformity_score": 0.445,
      "diversity_score": 0.991304347826087,
      "timestamp": "2025-08-18T14:47:19.424712"
    },
    {
      "txid": "bf7fafecaff1e16e079aaa3ab1bb31b014941a0d0ed8403cc379d1318fcab83e",
      "is_coinjoin": true,
      "detection_method": "wasabi",
      "score": 0.5,
      "reasons": [
        "Wasabi heuristic detection (0.1 BTC pattern)"
      ],
      "indicators": {
        "input_count": 61,
        "output_count": 115,
        "unique_input_addresses": 61,
        "unique_output_addresses": 115,
        "output_uniformity": 43,
        "input_diversity": 61,
        "transaction_size": 176
      },
      "wasabi_detected": true,
      "samourai_detected": false,
      "uniformity_score": 0.4,
      "diversity_score": 1.0,
      "timestamp": "2025-08-18T14:47:20.406582"
    },
    {
      "txid": "3a475e67d3d04eac293bcf9218023fe95028920f394ecbbee07feae7619b9499",
      "is_coinjoin": true,
      "detection_method": "wasabi",
      "score": 0.5,
      "reasons": [
        "Wasabi static detection (coordinator + equal outputs)",
        "Wasabi heuristic detection (0.1 BTC pattern)"
      ],
      "indicators": {
        "input_count": 72,
        "output_count": 119,
        "unique_input_addresses": 72,
        "unique_output_addresses": 119,
        "output_uniformity": 40,
        "input_diversity": 72,
        "transaction_size": 191
      },
      "wasabi_detected": true,
      "samourai_detected": false,
      "uniformity_score": 0.5210084033613446,
      "diversity_score": 1.0,
      "timestamp": "2025-08-18T14:47:21.410118"
    },
    {
      "txid": "6ad7682fcab32e6c051e693665c56aa1b236c4b05467da084a28440b7f68cb65",
      "is_coinjoin": true,
      "detection_method": "wasabi",
      "score": 0.4,
      "reasons": [
        "Wasabi heuristic detection (0.1 BTC pattern)"
      ],
      "indicators": {
        "input_count": 86,
        "output_count": 125,
        "unique_input_addresses": 86,
        "unique_output_addresses": 125,
        "output_uniformity": 45,
        "input_diversity": 86,
        "transaction_size": 211
      },
      "wasabi_detected": true,
      "samourai_detected": false,
      "uniformity_score": 0.536,
      "diversity_score": 1.0,
      "timestamp": "2025-08-18T14:47:22.441969"
    },
    {
      "txid": "0e7345a7cc12019f67f24ae88ca352268c42274836c55093f0e504e90ca91285",
      "is_coinjoin": true,
      "detection_method": "wasabi",
      "score": 0.5,
      "reasons": [
        "Wasabi heuristic detection (0.1 BTC pattern)"
      ],
      "indicators": {
        "input_count": 32,
        "output_count": 50,
        "unique_input_addresses": 32,
        "unique_output_addresses": 50,
        "output_uniformity": 24,
        "input_diversity": 32,
        "transaction_size": 82
      },
      "wasabi_detected": true,
      "samourai_detected": false,
      "uniformity_score": 0.46,
      "diversity_score": 1.0,
      "timestamp": "2025-08-18T14:47:23.443114"
    },
    {
      "txid": "aea9a0c469981eff9512e65fa2b6629efc885cef540e218c7c5d51212707ed07",
      "is_coinjoin": true,
      "detection_method": "wasabi",
      "score": 0.5,
      "reasons": [
        "Wasabi heuristic detection (0.1 BTC pattern)"
      ],
      "indicators": {
        "input_count": 72,
        "output_count": 113,
        "unique_input_addresses": 71,
        "unique_output_addresses": 113,
        "output_uniformity": 44,
        "input_diversity": 71,
        "transaction_size": 185
      },
      "wasabi_detected": true,
      "samourai_detected": false,
      "uniformity_score": 0.4690265486725664,
      "diversity_score": 0.9861111111111112,
      "timestamp": "2025-08-18T14:47:24.487007"
    },
    {
      "txid": "9393b613c57cdabe8d2e075154477670eb490d18c663019cc9b7d75a796c89f1",
      "is_coinjoin": true,
      "detection_method": "wasabi",
      "score": 0.5,
      "reasons": [
        "Wasabi heuristic detection (0.1 BTC pattern)"
      ],
      "indicators": {
        "input_count": 45,
        "output_count": 60,
        "unique_input_addresses": 45,
        "unique_output_addresses": 60,
        "output_uniformity": 20,
        "input_diversity": 45,
        "transaction_size": 105
      },
      "wasabi_detected": true,
      "samourai_detected": false,
      "uniformity_score": 0.55,
      "diversity_score": 1.0,
      "timestamp": "2025-08-18T14:47:25.480247"
    },
    {
      "txid": "553c4e3d8d63d7572d7c6b728a0d1e0f638a7351290f6cc91833773177491894",
      "is_coinjoin": true,
      "detection_method": "wasabi",
      "score": 0.4,
      "reasons": [
        "Wasabi heuristic detection (0.1 BTC pattern)"
      ],
      "indicators": {
        "input_count": 109,
        "output_count": 158,
        "unique_input_addresses": 109,
        "unique_output_addresses": 158,
        "output_uniformity": 70,
        "input_diversity": 109,
        "transaction_size": 267
      },
      "wasabi_detected": true,
      "samourai_detected": false,
      "uniformity_score": 0.46835443037974683,
      "diversity_score": 1.0,
      "timestamp": "2025-08-18T14:47:26.515368"
    },
    {
      "txid": "3e46ede9d1dbf66bea12f2fc40c0b27f5da7bd6f5214b51cae3f95df4c3837fd",
      "is_coinjoin": true,
      "detection_method": "wasabi",
      "score": 0.5,
      "reasons": [
        "Wasabi heuristic detection (0.1 BTC pattern)"
      ],
      "indicators": {
        "input_count": 70,
        "output_count": 106,
        "unique_input_addresses": 70,
        "unique_output_addresses": 106,
        "output_uniformity": 39,
        "input_diversity": 70,
        "transaction_size": 176
      },
      "wasabi_detected": true,
      "samourai_detected": false,
      "uniformity_score": 0.5094339622641509,
      "diversity_score": 1.0,
      "timestamp": "2025-08-18T14:47:27.507317"
    },
    {
      "txid": "2890ff9060b2c03889b3484ac14df1f5ef22aa5bfbcea5379a9ebf3c067abd86",
      "is_coinjoin": true,
      "detection_method": "wasabi",
      "score": 0.5,
      "reasons": [
        "Wasabi static detection (coordinator + equal outputs)",
        "Wasabi heuristic detection (0.1 BTC pattern)"
      ],
      "indicators": {
        "input_count": 67,
        "output_count": 100,
        "unique_input_addresses": 67,
        "unique_output_addresses": 100,
        "output_uniformity": 37,
        "input_diversity": 67,
        "transaction_size": 167
      },
      "wasabi_detected": true,
      "samourai_detected": false,
      "uniformity_score": 0.51,
      "diversity_score": 1.0,
      "timestamp": "2025-08-18T14:47:28.552276"
    },
    {
      "txid": "21b648d1ec354ec6e7ecdc097e69804272bb25146e6776eeb4cc5ba0c4619d90",
      "is_coinjoin": true,
      "detection_method": "wasabi",
      "score": 0.4,
      "reasons": [
        "Wasabi static detection (coordinator + equal outputs)",
        "Wasabi heuristic detection (0.1 BTC pattern)"
      ],
      "indicators": {
        "input_count": 112,
        "output_count": 180,
        "unique_input_addresses": 112,
        "unique_output_addresses": 180,
        "output_uniformity": 61,
        "input_diversity": 112,
        "transaction_size": 292
      },
      "wasabi_detected": true,
      "samourai_detected": false,
      "uniformity_score": 0.4777777777777778,
      "diversity_score": 1.0,
      "timestamp": "2025-08-18T14:47:29.587249"
    },
    {
      "txid": "29c62a70e9ff75705f3bd377c59d1a75f9312a28593835075ae5bb424c562744",
      "is_coinjoin": true,
      "detection_method": "wasabi",
      "score": 0.4,
      "reasons": [
        "Wasabi heuristic detection (0.1 BTC pattern)"
      ],
      "indicators": {
        "input_count": 124,
        "output_count": 229,
        "unique_input_addresses": 123,
        "unique_output_addresses": 229,
        "output_uniformity": 85,
        "input_diversity": 123,
        "transaction_size": 353
      },
      "wasabi_detected": true,
      "samourai_detected": false,
      "uniformity_score": 0.3930131004366812,
      "diversity_score": 0.9919354838709677,
      "timestamp": "2025-08-18T14:47:30.749451"
    },
    {
      "txid": "eefb423997afedddbe3f9834f2a622e28a4dc7c04b7ca1bff6d73b70c04a83b6",
      "is_coinjoin": true,
      "detection_method": "wasabi",
      "score": 0.5,
      "reasons": [
        "Wasabi heuristic detection (0.1 BTC pattern)"
      ],
      "indicators": {
        "input_count": 68,
        "output_count": 100,
        "unique_input_addresses": 68,
        "unique_output_addresses": 100,
        "output_uniformity": 45,
        "input_diversity": 68,
        "transaction_size": 168
      },
      "wasabi_detected": true,
      "samourai_detected": false,
      "uniformity_score": 0.44,
      "diversity_score": 1.0,
      "timestamp": "2025-08-18T14:47:31.718332"
    },
    {
      "txid": "332dec097ec72ca44930b33b8793c57b991b7cde1b86111fd273e6702c48a47b",
      "is_coinjoin": true,
      "detection_method": "wasabi",
      "score": 0.5,
      "reasons": [
        "Wasabi heuristic detection (0.1 BTC pattern)"
      ],
      "indicators": {
        "input_count": 42,
        "output_count": 80,
        "unique_input_addresses": 42,
        "unique_output_addresses": 80,
        "output_uniformity": 34,
        "input_diversity": 42,
        "transaction_size": 122
      },
      "wasabi_detected": true,
      "samourai_detected": false,
      "uniformity_score": 0.425,
      "diversity_score": 1.0,
      "timestamp": "2025-08-18T14:47:32.735097"
    },
    {
      "txid": "0d2dee14ef785bef8a3b02db2b084a803c0057d2473ad6e2b86d9ebbcf431ce1",
      "is_coinjoin": true,
      "detection_method": "wasabi",
      "score": 0.5,
      "reasons": [
        "Wasabi static detection (coordinator + equal outputs)",
        "Wasabi heuristic detection (0.1 BTC pattern)"
      ],
      "indicators": {
        "input_count": 42,
        "output_count": 69,
        "unique_input_addresses": 42,
        "unique_output_addresses": 69,
        "output_uniformity": 29,
        "input_diversity": 42,
        "transaction_size": 111
      },
      "wasabi_detected": true,
      "samourai_detected": false,
      "uniformity_score": 0.5942028985507246,
      "diversity_score": 1.0,
      "timestamp": "2025-08-18T14:47:33.711389"
    },
    {
      "txid": "7b7f7376de82e079efa21de8f762393dd2469e4c00ebf6d21a48d991c6fc17bf",
      "is_coinjoin": true,
      "detection_method": "wasabi",
      "score": 0.5,
      "reasons": [
        "Wasabi heuristic detection (0.1 BTC pattern)"
      ],
      "indicators": {
        "input_count": 52,
        "output_count": 86,
        "unique_input_addresses": 52,
        "unique_output_addresses": 86,
        "output_uniformity": 36,
        "input_diversity": 52,
        "transaction_size": 138
      },
      "wasabi_detected": true,
      "samourai_detected": false,
      "uniformity_score": 0.5348837209302325,
      "diversity_score": 1.0,
      "timestamp": "2025-08-18T14:47:34.721685"
    },
    {
      "txid": "b46660ef6e6fbb0016207435bf245bc9950acc9dafe052fa3683d9e9aaf7b217",
      "is_coinjoin": true,
      "detection_method": "wasabi",
      "score": 0.5,
      "reasons": [
        "Wasabi heuristic detection (0.1 BTC pattern)"
      ],
      "indicators": {
        "input_count": 63,
        "output_count": 115,
        "unique_input_addresses": 63,
        "unique_output_addresses": 115,
        "output_uniformity": 45,
        "input_diversity": 63,
        "transaction_size": 178
      },
      "wasabi_detected": true,
      "samourai_detected": false,
      "uniformity_score": 0.4260869565217391,
      "diversity_score": 1.0,
      "timestamp": "2025-08-18T14:47:35.794251"
    },
    {
      "txid": "4311d0961830d981c10778f8f731a1bbd3112c05c4cf0d5ecd05e72a71df2918",
      "is_coinjoin": true,
      "detection_method": "wasabi",
      "score": 0.4,
      "reasons": [
        "Wasabi heuristic detection (0.1 BTC pattern)"
      ],
      "indicators": {
        "input_count": 73,
        "output_count": 129,
        "unique_input_addresses": 73,
        "unique_output_addresses": 129,
        "output_uniformity": 50,
        "input_diversity": 73,
        "transaction_size": 202
      },
      "wasabi_detected": true,
      "samourai_detected": false,
      "uniformity_score": 0.4573643410852713,
      "diversity_score": 1.0,
      "timestamp": "2025-08-18T14:47:36.817105"
    },
    {
      "txid": "d18989e6e330c4c953d310e209275bda4990cb9543f3fd27d328111ad9385f61",
      "is_coinjoin": true,
      "detection_method": "wasabi",
      "score": 0.4,
      "reasons": [
        "Wasabi heuristic detection (0.1 BTC pattern)"
      ],
      "indicators": {
        "input_count": 77,
        "output_count": 127,
        "unique_input_addresses": 77,
        "unique_output_addresses": 127,
        "output_uniformity": 47,
        "input_diversity": 77,
        "transaction_size": 204
      },
      "wasabi_detected": true,
      "samourai_detected": false,
      "uniformity_score": 0.4881889763779528,
      "diversity_score": 1.0,
      "timestamp": "2025-08-18T14:47:37.856414"
    },
    {
      "txid": "33fea9d7fef708c95a5d52c0a721016d876bc73d96faff1e64b28911aca3c9b9",
      "is_coinjoin": true,
      "detection_method": "wasabi",
      "score": 0.4,
      "reasons": [
        "Wasabi heuristic detection (0.1 BTC pattern)"
      ],
      "indicators": {
        "input_count": 108,
        "output_count": 174,
        "unique_input_addresses": 107,
        "unique_output_addresses": 174,
        "output_uniformity": 64,
        "input_diversity": 107,
        "transaction_size": 282
      },
      "wasabi_detected": true,
      "samourai_detected": false,
      "uniformity_score": 0.4367816091954023,
      "diversity_score": 0.9907407407407407,
      "timestamp": "2025-08-18T14:47:39.085347"
    },
    {
      "txid": "ee1ff288be77acc2898c97251b672ffdce1f44d02ae7d1d65574db73f2cc128c",
      "is_coinjoin": true,
      "detection_method": "wasabi",
      "score": 0.5,
      "reasons": [
        "Wasabi heuristic detection (0.1 BTC pattern)"
      ],
      "indicators": {
        "input_count": 56,
        "output_count": 120,
        "unique_input_addresses": 56,
        "unique_output_addresses": 120,
        "output_uniformity": 48,
        "input_diversity": 56,
        "transaction_size": 176
      },
      "wasabi_detected": true,
      "samourai_detected": false,
      "uniformity_score": 0.4,
      "diversity_score": 1.0,
      "timestamp": "2025-08-18T14:47:40.118281"
    },
    {
      "txid": "ae910584b6e513932389a580e248918a448f5d7ea9c43907352247d03f6d59d6",
      "is_coinjoin": true,
      "detection_method": "wasabi",
      "score": 0.4,
      "reasons": [
        "Wasabi heuristic detection (0.1 BTC pattern)"
      ],
      "indicators": {
        "input_count": 99,
        "output_count": 169,
        "unique_input_addresses": 99,
        "unique_output_addresses": 169,
        "output_uniformity": 55,
        "input_diversity": 99,
        "transaction_size": 268
      },
      "wasabi_detected": true,
      "samourai_detected": false,
      "uniformity_score": 0.4556213017751479,
      "diversity_score": 1.0,
      "timestamp": "2025-08-18T14:47:41.210133"
    }
  ]
}